Metadata-Version: 2.1
Name: perfect-hash
Version: 0.4.3
Summary: creating perfect minimal hash function
Home-page: https://github.com/ilanschnell/perfect-hash
Author: Ilan Schnell
Author-email: ilanschnell@gmail.com
License: BSD
Classifier: License :: OSI Approved :: BSD License
Classifier: Development Status :: 5 - Production/Stable
Classifier: Intended Audience :: Developers
Classifier: Operating System :: OS Independent
Classifier: Programming Language :: Python :: 2
Classifier: Programming Language :: Python :: 2.7
Classifier: Programming Language :: Python :: 3
Classifier: Programming Language :: Python :: 3.5
Classifier: Programming Language :: Python :: 3.6
Classifier: Programming Language :: Python :: 3.7
Classifier: Programming Language :: Python :: 3.8
Classifier: Programming Language :: Python :: 3.9
Classifier: Programming Language :: Python :: 3.10
Classifier: Programming Language :: Python :: 3.11
Classifier: Programming Language :: Python :: 3.12
Classifier: Topic :: Utilities
License-File: LICENSE.txt
